{"_version_": 1751804935057440769, "access_restricted": false, "aka": ["http://www.loc.gov/item/2020587086/", "http://www.loc.gov/resource/g3844b.wd000023/", "https://hdl.loc.gov/loc.gmd/g3844b.wd000023", "http://lccn.loc.gov/2020587086"], "call_number": ["G3844.B2 1844 .L8"], "campaigns": [], "contributor_names": ["Lucas, Fielding, Jr., 1781-1854, cartographer, publisher."], "contributors": [{"lucas, fielding": "https://www.loc.gov/search/?fa=contributor:lucas,+fielding&fo=json"}], "control_number": "", "created_published": ["[Baltimore, MD] : Published by F. Lucas, Jr., no. 170 Baltimore Street, [1844?]"], "date": "1844-01-01", "dates": [{"1844": "https://www.loc.gov/search/?dates=1844/1844&fo=json"}], "description": ["Depths shown by soundings. Shows wards and railroads. Includes notes and index to points of interest. LC copy annotated in red pencil, probably showing additional railroad lines. Available also through the Library of Congress Web site as a raster image."], "digital_id": ["https://hdl.loc.gov/loc.gmd/g3844b.wd000023"], "digitized": true, "display_offsite": true, "extract_timestamp": "2021-10-29T22:33:21.313Z", "extract_urls": ["http://www.loc.gov/item/2020587086#gmd.mar", "http://lccn.loc.gov/2020587086#catalog-split-06"], "format": [{"map": "https://www.loc.gov/search/?fa=original_format:map&fo=json"}], "genre": ["Maps"], "group": ["gmd.mar", "catalog-split-06", "catalog", "general-maps", "main-catalog-split-06", "main-catalog"], "hassegments": false, "id": "http://www.loc.gov/item/2020587086/", "image_url": ["https://tile.loc.gov/storage-services/service/gmd/gmd384/g3844/g3844b/wd000023.gif", "https://tile.loc.gov/storage-services/service/gmd/gmd384/g3844/g3844b/wd000023.gif#h=150&w=145", "https://tile.loc.gov/image-services/iiif/service:gmd:gmd384:g3844:g3844b:wd000023/full/pct:12.5/0/default.jpg#h=492&w=477", "https://tile.loc.gov/image-services/iiif/service:gmd:gmd384:g3844:g3844b:wd000023/full/pct:25/0/default.jpg#h=984&w=954"], "index": 1, "item": {"call_number": ["G3844.B2 1844 .L8"], "contributors": ["Lucas, Fielding, Jr., 1781-1854, cartographer, publisher."], "created_published": ["[Baltimore, MD] : Published by F. Lucas, Jr., no. 170 Baltimore Street, [1844?]"], "date": "1844", "digital_id": ["https://hdl.loc.gov/loc.gmd/g3844b.wd000023"], "format": ["cartographic"], "genre": ["Maps"], "language": ["eng"], "location": ["Maryland--Baltimore", "Baltimore (Md.)"], "medium": ["1 map : hand colored ; 23 x 31 cm"], "notes": ["Depths shown by soundings.", "Shows wards and railroads.", "Includes notes and index to points of interest.", "LC copy annotated in red pencil, probably showing additional railroad lines.", "Available also through the Library of Congress Web site as a raster image."], "number_former_id": ["https://www.loc.gov/item/2020587086", "https://www.loc.gov/item/21448255"], "repository": ["Library of Congress Geography and Map Division Washington, D.C. 20540-4650 USA dcu"], "subjects": ["Local transit--Maryland--Baltimore--Maps", "Election districts--Maryland--Baltimore--Maps", "Baltimore (Md.)--Maps", "United States--Maryland--Baltimore"], "title": "Plan of Baltimore."}, "language": ["english"], "languages": [{"english": "https://www.loc.gov/search/?fa=language:english&fo=json"}], "library_of_congress_control_number": "2020587086", "location": ["united states", "maryland", "baltimore"], "location_city": ["baltimore"], "location_country": ["united states"], "location_state": ["maryland"], "locations": [{"baltimore": "https://www.loc.gov/search/?fa=location:baltimore&fo=json"}, {"maryland": "https://www.loc.gov/search/?fa=location:maryland&fo=json"}, {"united states": "https://www.loc.gov/search/?fa=location:united+states&fo=json"}], "locations_city": [{"baltimore": "https://www.loc.gov/search/?fa=location_city:baltimore&fo=json"}], "locations_country": [{"united states": "https://www.loc.gov/search/?fa=location_country:united+states&fo=json"}], "locations_state": [{"maryland": "https://www.loc.gov/search/?fa=location_state:maryland&fo=json"}], "medium": ["1 map : hand colored ; 23 x 31 cm"], "mime_type": ["image/gif", "image/tiff", "image/jpeg", "image/jp2"], "notes": ["Depths shown by soundings.", "Shows wards and railroads.", "Includes notes and index to points of interest.", "LC copy annotated in red pencil, probably showing additional railroad lines.", "Available also through the Library of Congress Web site as a raster image."], "number": ["http://www.loc.gov/item/2020587086", "2020587086", "sheet", "http://www.loc.gov/item/21448255", "2021-07-22t07:58:40"], "number_carrier_type": ["sheet"], "number_former_id": ["http://www.loc.gov/item/2020587086", "http://www.loc.gov/item/21448255"], "number_lccn": ["2020587086"], "number_source_modified": ["2021-07-22t07:58:40"], "online_format": ["image"], "original_format": ["map"], "other_formats": [{"label": "MARCXML Record", "link": "https://lccn.loc.gov/2020587086/marcxml"}, {"label": "MODS Record", "link": "https://lccn.loc.gov/2020587086/mods"}, {"label": "Dublin Core Record", "link": "https://lccn.loc.gov/2020587086/dc"}], "other_title": [], "partof": [{"count": 3759, "title": "cities and towns", "url": "https://www.loc.gov/collections/cities-and-towns/?fo=json"}, {"count": 56275, "title": "geography and map division", "url": "https://www.loc.gov/search/?fa=partof:geography+and+map+division&fo=json"}, {"count": 503429, "title": "american memory", "url": "https://www.loc.gov/search/?fa=partof:american+memory&fo=json"}, {"count": 1496879, "title": "catalog", "url": "https://www.loc.gov/search/?fa=partof:catalog&fo=json"}], "repository": ["Library of Congress Geography and Map Division Washington, D.C. 20540-4650 USA dcu"], "resources": [{"files": 1, "image": "https://tile.loc.gov/storage-services/service/gmd/gmd384/g3844/g3844b/wd000023.gif", "url": "https://www.loc.gov/resource/g3844b.wd000023/"}], "rights": ["<p>The maps in the Map Collections materials were either published prior to \r1922, produced by the United States government, or both (see catalogue \rrecords that accompany each map for information regarding date of \rpublication and source). The Library of Congress is providing access to \rthese materials for educational and research purposes and is not aware of \rany U.S. copyright protection (see Title 17 of the United States Code) or any \rother restrictions in the Map Collection materials.\r</p>\r<p>Note that the written permission of the copyright owners and/or other rights \rholders (such as publicity and/or privacy rights) is required for distribution, \rreproduction, or other use of protected items beyond that allowed by fair use \ror other statutory exemptions.  Responsibility for making an independent \rlegal assessment of an item and securing any necessary permissions \rultimately rests with persons desiring to use the item.\r</p>\r<p>Credit Line: Library of Congress, Geography and Map Division. </p>"], "score": 16.539604, "shard": "01", "shelf_id": "G3844.B2 1844 .L8", "site": ["ammem", "catalog"], "subject": ["local transit", "election districts", "united states", "maps", "baltimore (md.)", "maryland", "baltimore"], "subject_headings": ["Local transit--Maryland--Baltimore--Maps", "Election districts--Maryland--Baltimore--Maps", "Baltimore (Md.)--Maps", "United States--Maryland--Baltimore"], "subjects": [{"baltimore": "https://www.loc.gov/search/?fa=subject:baltimore&fo=json"}, {"baltimore (md.)": "https://www.loc.gov/search/?fa=subject:baltimore+%28md.%29&fo=json"}, {"election districts": "https://www.loc.gov/search/?fa=subject:election+districts&fo=json"}, {"local transit": "https://www.loc.gov/search/?fa=subject:local+transit&fo=json"}, {"maps": "https://www.loc.gov/search/?fa=subject:maps&fo=json"}, {"maryland": "https://www.loc.gov/search/?fa=subject:maryland&fo=json"}, {"united states": "https://www.loc.gov/search/?fa=subject:united+states&fo=json"}], "timestamp": "2022-12-10T05:49:33.784Z", "title": "Plan of Baltimore.", "type": ["map"], "url": "https://www.loc.gov/item/2020587086/"}